README.md
setup.cfg
setup.py
ocds_api.client.python.egg-info/PKG-INFO
ocds_api.client.python.egg-info/SOURCES.txt
ocds_api.client.python.egg-info/dependency_links.txt
ocds_api.client.python.egg-info/entry_points.txt
ocds_api.client.python.egg-info/not-zip-safe
ocds_api.client.python.egg-info/requires.txt
ocds_api.client.python.egg-info/top_level.txt
ocds_client/__init__.py
ocds_client/clients.py
ocds_client/exceptions.py
ocds_client/sync.py
ocds_client/templates.py
ocds_client/utils.py
ocds_client/tests/__init__.py
ocds_client/tests/conftest.py
ocds_client/tests/test_clients.py
ocds_client/tests/test_sync.py
ocds_client/tests/test_templates.py
ocds_client/tests/test_utils.py
ocds_client/tests/utils.py