Metadata-Version: 2.1
Name: ocds-api.client.python
Version: 0.0.1b0
Summary: UNKNOWN
Home-page: https://github.com/openprocurement/ocds-api.client.python
Author: Quintagroup, Ltd.
Author-email: info@quintagroup.com
License: Apache Software License 2.0
Keywords: ocds-client,ocds-api,ocds
Platform: UNKNOWN
Classifier: Programming Language :: Python :: 3.6
Classifier: Programming Language :: Python :: 3.7
Classifier: Development Status :: 4 - Beta
Provides-Extra: test
